mmtools/__init__.py
mmtools/arguments.py
mmtools/config.py
mmtools/mattermost.py
mmtools/status.py
mmtools/watch.py
mmtools/etc/config
mmtools-0.0.39.dist-info/METADATA
mmtools-0.0.39.dist-info/WHEEL
mmtools-0.0.39.dist-info/entry_points.txt
mmtools-0.0.39.dist-info/licenses/LICENSE
mmtools-0.0.39.dist-info/RECORD
