Metadata-Version: 2.3
Name: mmtools
Version: 0.0.39
Summary: mmtools
Project-URL: Homepage, https://github.com/frbor/mmtools
Author-email: Fredrik Borg <fredrikb.borg@gmail.com>
License-File: LICENSE
Classifier: Development Status :: 4 - Beta
Classifier: License :: OSI Approved :: ISC License (ISCL)
Classifier: Topic :: Utilities
Requires-Python: >=3.11
Requires-Dist: caep==1.1.*
Requires-Dist: dbus-python==1.3.2
Requires-Dist: mattermostdriver==7.3.*
Requires-Dist: notify2==0.3.*
Requires-Dist: passpy==1.0.2
Requires-Dist: requests==2.32.*
